src/sibylpy/__init__.py
src/sibylpy/exceptions.py
src/sibylpy/types/__init__.py
src/sibylpy/types/bans.py
src/sibylpy/types/permission.py
src/sibylpy/types/token.py
sibylpy-0.0.2.dist-info/LICENSE
sibylpy-0.0.2.dist-info/WHEEL
sibylpy-0.0.2.dist-info/METADATA
sibylpy-0.0.2.dist-info/RECORD
